[
  {
    "id": "exp_hook_retention_pct_20260409_174639",
    "indicator_key": "hook_retention_pct",
    "tool_id": "pearson_r",
    "tool_name": "Pearson Correlation",
    "target": "views",
    "parameters": {
      "target": "views",
      "transform_target": "log10",
      "confounds": [],
      "min_n": 50
    },
    "outputs": {
      "r": -0.04996365118112891,
      "p_value": 0.33785262041648817,
      "n": 370,
      "ci_low": -0.1511493569300314,
      "ci_high": 0.05225822861249729,
      "rho": 0.12148035871238054,
      "p_rho": 0.019414347603201102
    },
    "n_videos": 370,
    "status": "discovery",
    "ran_at": "2026-04-09T17:46:39.729613Z"
  },
  {
    "id": "exp_final_5pct_retention_20260409_174639",
    "indicator_key": "final_5pct_retention",
    "tool_id": "pearson_r",
    "tool_name": "Pearson Correlation",
    "target": "views",
    "parameters": {
      "target": "views",
      "transform_target": "log10",
      "confounds": [],
      "min_n": 50
    },
    "outputs": {
      "r": 0.4715732924173845,
      "p_value": 6.953837184165362e-22,
      "n": 370,
      "ci_low": 0.38828625713942294,
      "ci_high": 0.5472189134956179,
      "rho": 0.47151477454466556,
      "p_rho": 7.046089840690292e-22
    },
    "n_videos": 370,
    "status": "discovery",
    "ran_at": "2026-04-09T17:46:39.734344Z"
  },
  {
    "id": "exp_mid_video_cliff_20260409_174639",
    "indicator_key": "mid_video_cliff",
    "tool_id": "pearson_r",
    "tool_name": "Pearson Correlation",
    "target": "views",
    "parameters": {
      "target": "views",
      "transform_target": "log10",
      "confounds": [],
      "min_n": 50
    },
    "outputs": {
      "r": 0.17664005735272306,
      "p_value": 0.0006422391456777828,
      "n": 370,
      "ci_low": 0.07605407756931436,
      "ci_high": 0.2736671335038069,
      "rho": 0.44150866781105136,
      "p_rho": 4.389971733039257e-19
    },
    "n_videos": 370,
    "status": "discovery",
    "ran_at": "2026-04-09T17:46:39.742747Z"
  },
  {
    "id": "exp_retention_entropy_20260409_174639",
    "indicator_key": "retention_entropy",
    "tool_id": "pearson_r",
    "tool_name": "Pearson Correlation",
    "target": "views",
    "parameters": {
      "target": "views",
      "transform_target": "log10",
      "confounds": [],
      "min_n": 50
    },
    "outputs": {
      "r": 0.4651759674555697,
      "p_value": 2.893882663662914e-21,
      "n": 370,
      "ci_low": 0.3813045513087749,
      "ci_high": 0.5414520170432291,
      "rho": 0.5556594001140711,
      "p_rho": 2.308541506976829e-31
    },
    "n_videos": 370,
    "status": "discovery",
    "ran_at": "2026-04-09T17:46:39.753885Z"
  },
  {
    "id": "exp_hook_drop_rate_20260409_174639",
    "indicator_key": "hook_drop_rate",
    "tool_id": "pearson_r",
    "tool_name": "Pearson Correlation",
    "target": "views",
    "parameters": {
      "target": "views",
      "transform_target": "log10",
      "confounds": [],
      "min_n": 50
    },
    "outputs": {
      "r": -0.4019295720284731,
      "p_value": 8.486466158819269e-16,
      "n": 370,
      "ci_low": -0.4840493846954565,
      "ci_high": -0.31279179453946787,
      "rho": -0.3906557665416386,
      "p_rho": 6.134625121496267e-15
    },
    "n_videos": 370,
    "status": "discovery",
    "ran_at": "2026-04-09T17:46:39.804537Z"
  }
]